{
    "timeZone": "Asia/Jerusalem",
    "dependencies": {
      "enabledAdvancedServices": [{
        "userSymbol": "Calendar",
        "serviceId": "calendar",
        "version": "v3"
      }],
      "libraries": [{
        "userSymbol": "OAuth2",
        "libraryId": "1B7FSrk5Zi6L1rSxxTDgDEUsPzlukDsi4KGuTMorsTQHhGBzBkMun4iDF",
        "version": "35"
      }]
    },
    "webapp": {
      "access": "ANYONE",
      "executeAs": "USER_ACCESSING"
    },
    "exceptionLogging": "STACKDRIVER",
    "oauthScopes": ["https://www.googleapis.com/auth/userinfo.email", "https://www.googleapis.com/auth/calendar.addons.execute", "https://www.googleapis.com/auth/calendar.events.readonly", "https://www.googleapis.com/auth/script.external_request", "https://www.googleapis.com/auth/script.scriptapp"],
    "urlFetchWhitelist": ["https://app.gong.io/", "https://webhooks.gong.io/"],
    "runtimeVersion": "V8",
    "addOns": {
      "common": {
        "name": "Meeting Scheduler",
        "logoUrl": "https://lh3.googleusercontent.com/-Uv8IX_wOZBY/Xef-rzpQabI/AAAAAAAABHI/lq3G2E6RfUAkFuQ8TFu-3eol6AB_m6ZhgCLcBGAsYHQ/s400/Gong%2BLogo96.png"
      },
      "calendar": {
        "conferenceSolution": [{
          "onCreateFunction": "createConference",
          "id": "myWebConference",
          "name": "Meeting tester",
          "logoUrl": "https://lh3.googleusercontent.com/-Uv8IX_wOZBY/Xef-rzpQabI/AAAAAAAABHI/lq3G2E6RfUAkFuQ8TFu-3eol6AB_m6ZhgCLcBGAsYHQ/s400/Gong%2BLogo96.png"
        }],
        "createSettingsUrlFunction": "createSettingsUrl"
      }
    }
  }